odoo/addons/account_invoice_mode_at_shipping/README.rst
odoo/addons/account_invoice_mode_at_shipping/__init__.py
odoo/addons/account_invoice_mode_at_shipping/__manifest__.py
odoo/addons/account_invoice_mode_at_shipping/data/queue_job_data.xml
odoo/addons/account_invoice_mode_at_shipping/i18n/account_invoice_mode_at_shipping.pot
odoo/addons/account_invoice_mode_at_shipping/i18n/ca.po
odoo/addons/account_invoice_mode_at_shipping/i18n/fr.po
odoo/addons/account_invoice_mode_at_shipping/models/__init__.py
odoo/addons/account_invoice_mode_at_shipping/models/res_partner.py
odoo/addons/account_invoice_mode_at_shipping/models/stock_move.py
odoo/addons/account_invoice_mode_at_shipping/models/stock_picking.py
odoo/addons/account_invoice_mode_at_shipping/readme/CONTRIBUTORS.rst
odoo/addons/account_invoice_mode_at_shipping/readme/CREDITS.rst
odoo/addons/account_invoice_mode_at_shipping/readme/DESCRIPTION.rst
odoo/addons/account_invoice_mode_at_shipping/static/description/icon.png
odoo/addons/account_invoice_mode_at_shipping/static/description/index.html
odoo/addons/account_invoice_mode_at_shipping/tests/__init__.py
odoo/addons/account_invoice_mode_at_shipping/tests/test_invoice_mode_at_shipping.py
odoo14_addon_account_invoice_mode_at_shipping-14.0.1.2.0.dist-info/METADATA
odoo14_addon_account_invoice_mode_at_shipping-14.0.1.2.0.dist-info/WHEEL
odoo14_addon_account_invoice_mode_at_shipping-14.0.1.2.0.dist-info/top_level.txt
odoo14_addon_account_invoice_mode_at_shipping-14.0.1.2.0.dist-info/RECORD
